fullmetalalchemy/__init__.py
fullmetalalchemy/basetable.py
fullmetalalchemy/batch.py
fullmetalalchemy/connection.py
fullmetalalchemy/create.py
fullmetalalchemy/delete.py
fullmetalalchemy/drop.py
fullmetalalchemy/exceptions.py
fullmetalalchemy/features.py
fullmetalalchemy/insert.py
fullmetalalchemy/py.typed
fullmetalalchemy/records.py
fullmetalalchemy/select.py
fullmetalalchemy/session.py
fullmetalalchemy/sessiontable.py
fullmetalalchemy/table.py
fullmetalalchemy/test_setup.py
fullmetalalchemy/type_convert.py
fullmetalalchemy/types.py
fullmetalalchemy/update.py
fullmetalalchemy/_internal/__init__.py
fullmetalalchemy/_internal/converters.py
fullmetalalchemy/_internal/helpers.py
fullmetalalchemy/_internal/query_builders.py
fullmetalalchemy/_internal/validators.py
fullmetalalchemy/async_api/__init__.py
fullmetalalchemy/async_api/batch.py
fullmetalalchemy/async_api/create.py
fullmetalalchemy/async_api/delete.py
fullmetalalchemy/async_api/drop.py
fullmetalalchemy/async_api/insert.py
fullmetalalchemy/async_api/py.typed
fullmetalalchemy/async_api/select.py
fullmetalalchemy/async_api/session.py
fullmetalalchemy/async_api/sessiontable.py
fullmetalalchemy/async_api/table.py
fullmetalalchemy/async_api/update.py
fullmetalalchemy-2.6.0.dist-info/LICENSE
fullmetalalchemy-2.6.0.dist-info/METADATA
fullmetalalchemy-2.6.0.dist-info/WHEEL
fullmetalalchemy-2.6.0.dist-info/top_level.txt
fullmetalalchemy-2.6.0.dist-info/RECORD
