Metadata-Version: 2.1
Name: fullmetalalchemy
Version: 2.6.0
Summary: Easy-to-use helpers for SQL table changes with SQLAlchemy.
Author: Odos Matthews
License: MIT License
Project-URL: Homepage, https://github.com/eddiethedean/fullmetalalchemy
Project-URL: Repository, https://github.com/eddiethedean/fullmetalalchemy
Classifier: Development Status :: 4 - Beta
Classifier: Intended Audience :: Developers
Classifier: License :: OSI Approved :: MIT License
Classifier: Programming Language :: Python :: 3
Classifier: Programming Language :: Python :: 3 :: Only
Classifier: Programming Language :: Python :: 3.8
Classifier: Programming Language :: Python :: 3.9
Classifier: Programming Language :: Python :: 3.10
Classifier: Programming Language :: Python :: 3.11
Classifier: Programming Language :: Python :: 3.12
Classifier: Programming Language :: Python :: 3.13
Classifier: Topic :: Database
Requires-Python: >=3.8
License-File: LICENSE
Requires-Dist: SQLAlchemy<3,>=1.4
Requires-Dist: tinytim>=0.1.2
Requires-Dist: frozendict>=2.4
Provides-Extra: async
Requires-Dist: greenlet>=3.0; extra == "async"
Requires-Dist: aiosqlite>=0.19; extra == "async"
Requires-Dist: asyncpg>=0.29; extra == "async"
Requires-Dist: aiomysql>=0.2; extra == "async"
Provides-Extra: dev
Requires-Dist: pytest>=8; extra == "dev"
Requires-Dist: pytest-cov>=4; extra == "dev"
Requires-Dist: pytest-asyncio>=0.23; extra == "dev"
Requires-Dist: greenlet>=3.0; extra == "dev"
Requires-Dist: aiosqlite>=0.19; extra == "dev"
Requires-Dist: mypy>=1.10; extra == "dev"
Requires-Dist: ruff>=0.6; extra == "dev"
Requires-Dist: ty>=0.1; extra == "dev"
Requires-Dist: tox>=4; extra == "dev"
Provides-Extra: pandas
Requires-Dist: pandas>=1.5.0; extra == "pandas"
Provides-Extra: testing
Requires-Dist: pytest>=8; extra == "testing"
Requires-Dist: pytest-cov>=4; extra == "testing"
Requires-Dist: pytest-asyncio>=0.23; extra == "testing"
Requires-Dist: greenlet>=3.0; extra == "testing"
Requires-Dist: aiosqlite>=0.19; extra == "testing"
Requires-Dist: psycopg[binary]>=3.1; extra == "testing"
Requires-Dist: PyMySQL>=1.1; extra == "testing"
Requires-Dist: testing.postgresql>=1.3; extra == "testing"
Requires-Dist: testing.mysqld>=1.4; extra == "testing"
